{"config":{"output_file":null,"full_docs":false,"pub_only":true,"reachable_only":true,"distro_crate":false,"signatures":false,"borrow_data":false},"version":"0.19.0","compilation":{"directory":"/home/senick/.cargo/registry/src/github.com-1ecc6299db9ec823/wasm-logger-0.2.0","program":"/home/senick/.rustup/toolchains/nightly-x86_64-unknown-linux-gnu/bin/rls","arguments":["--crate-name","wasm_logger","--edition=2018","/home/senick/.cargo/registry/src/github.com-1ecc6299db9ec823/wasm-logger-0.2.0/src/lib.rs","--json=diagnostic-rendered-ansi","--crate-type","lib","--emit=dep-info,metadata","-C","embed-bitcode=no","-C","debuginfo=2","-C","metadata=c711adc1b90a9341","-C","extra-filename=-c711adc1b90a9341","--out-dir","/home/senick/Documentos/Projects/Rust/LowStream/target/rls/debug/deps","-L","dependency=/home/senick/Documentos/Projects/Rust/LowStream/target/rls/debug/deps","--extern","log=/home/senick/Documentos/Projects/Rust/LowStream/target/rls/debug/deps/liblog-39a9c9bb9b8c3de3.rmeta","--extern","wasm_bindgen=/home/senick/Documentos/Projects/Rust/LowStream/target/rls/debug/deps/libwasm_bindgen-d78aa1af24c20227.rmeta","--extern","web_sys=/home/senick/Documentos/Projects/Rust/LowStream/target/rls/debug/deps/libweb_sys-6c5602395942096b.rmeta","--cap-lints","allow","--error-format=json","--sysroot","/home/senick/.rustup/toolchains/nightly-x86_64-unknown-linux-gnu"],"output":"/home/senick/Documentos/Projects/Rust/LowStream/target/rls/debug/deps/libwasm_logger-c711adc1b90a9341.rmeta"},"prelude":{"crate_id":{"name":"wasm_logger","disambiguator":[264531760740814425,11413051847785420743]},"crate_root":"/home/senick/.cargo/registry/src/github.com-1ecc6299db9ec823/wasm-logger-0.2.0/src","external_crates":[{"file_name":"/home/senick/.cargo/registry/src/github.com-1ecc6299db9ec823/wasm-logger-0.2.0/src/lib.rs","num":1,"id":{"name":"std","disambiguator":[8110947160963498775,9547971581106319675]}},{"file_name":"/home/senick/.cargo/registry/src/github.com-1ecc6299db9ec823/wasm-logger-0.2.0/src/lib.rs","num":2,"id":{"name":"core","disambiguator":[2858088706689600179,17176650857302713463]}},{"file_name":"/home/senick/.cargo/registry/src/github.com-1ecc6299db9ec823/wasm-logger-0.2.0/src/lib.rs","num":3,"id":{"name":"compiler_builtins","disambiguator":[9928116384346554225,16446923409091048292]}},{"file_name":"/home/senick/.cargo/registry/src/github.com-1ecc6299db9ec823/wasm-logger-0.2.0/src/lib.rs","num":4,"id":{"name":"rustc_std_workspace_core","disambiguator":[8920863043171661139,6394972819860350927]}},{"file_name":"/home/senick/.cargo/registry/src/github.com-1ecc6299db9ec823/wasm-logger-0.2.0/src/lib.rs","num":5,"id":{"name":"alloc","disambiguator":[16318053409528761729,5855121237454704042]}},{"file_name":"/home/senick/.cargo/registry/src/github.com-1ecc6299db9ec823/wasm-logger-0.2.0/src/lib.rs","num":6,"id":{"name":"libc","disambiguator":[14512907882251490092,5479590506689914850]}},{"file_name":"/home/senick/.cargo/registry/src/github.com-1ecc6299db9ec823/wasm-logger-0.2.0/src/lib.rs","num":7,"id":{"name":"unwind","disambiguator":[14830404840608773336,5186655723863612804]}},{"file_name":"/home/senick/.cargo/registry/src/github.com-1ecc6299db9ec823/wasm-logger-0.2.0/src/lib.rs","num":8,"id":{"name":"cfg_if","disambiguator":[5979771489467164496,12360320737082644560]}},{"file_name":"/home/senick/.cargo/registry/src/github.com-1ecc6299db9ec823/wasm-logger-0.2.0/src/lib.rs","num":9,"id":{"name":"hashbrown","disambiguator":[1921189340940142061,18314585673924454475]}},{"file_name":"/home/senick/.cargo/registry/src/github.com-1ecc6299db9ec823/wasm-logger-0.2.0/src/lib.rs","num":10,"id":{"name":"rustc_std_workspace_alloc","disambiguator":[17750417031284557414,11704004160436595305]}},{"file_name":"/home/senick/.cargo/registry/src/github.com-1ecc6299db9ec823/wasm-logger-0.2.0/src/lib.rs","num":11,"id":{"name":"rustc_demangle","disambiguator":[8072307049108009892,14304054004335399885]}},{"file_name":"/home/senick/.cargo/registry/src/github.com-1ecc6299db9ec823/wasm-logger-0.2.0/src/lib.rs","num":12,"id":{"name":"addr2line","disambiguator":[889627186555995942,5791187066388706159]}},{"file_name":"/home/senick/.cargo/registry/src/github.com-1ecc6299db9ec823/wasm-logger-0.2.0/src/lib.rs","num":13,"id":{"name":"gimli","disambiguator":[9274895086208594573,8746659122264388963]}},{"file_name":"/home/senick/.cargo/registry/src/github.com-1ecc6299db9ec823/wasm-logger-0.2.0/src/lib.rs","num":14,"id":{"name":"object","disambiguator":[1228701392978562219,9152616415160251926]}},{"file_name":"/home/senick/.cargo/registry/src/github.com-1ecc6299db9ec823/wasm-logger-0.2.0/src/lib.rs","num":15,"id":{"name":"miniz_oxide","disambiguator":[3326509426007454723,8461783385980217594]}},{"file_name":"/home/senick/.cargo/registry/src/github.com-1ecc6299db9ec823/wasm-logger-0.2.0/src/lib.rs","num":16,"id":{"name":"adler","disambiguator":[7972146817127849776,6060534244587001507]}},{"file_name":"/home/senick/.cargo/registry/src/github.com-1ecc6299db9ec823/wasm-logger-0.2.0/src/lib.rs","num":17,"id":{"name":"panic_unwind","disambiguator":[5700689631817767545,76538919792707917]}},{"file_name":"/home/senick/.cargo/registry/src/github.com-1ecc6299db9ec823/wasm-logger-0.2.0/src/lib.rs","num":18,"id":{"name":"log","disambiguator":[7458700285163586467,11764782356929064942]}},{"file_name":"/home/senick/.cargo/registry/src/github.com-1ecc6299db9ec823/wasm-logger-0.2.0/src/lib.rs","num":19,"id":{"name":"cfg_if","disambiguator":[9770393089648805934,3221467257793745609]}},{"file_name":"/home/senick/.cargo/registry/src/github.com-1ecc6299db9ec823/wasm-logger-0.2.0/src/lib.rs","num":20,"id":{"name":"wasm_bindgen","disambiguator":[1772084657087280073,17511840099581303155]}},{"file_name":"/home/senick/.cargo/registry/src/github.com-1ecc6299db9ec823/wasm-logger-0.2.0/src/lib.rs","num":21,"id":{"name":"wasm_bindgen_macro","disambiguator":[17147547384455164450,1354468003205187509]}},{"file_name":"/home/senick/.cargo/registry/src/github.com-1ecc6299db9ec823/wasm-logger-0.2.0/src/lib.rs","num":22,"id":{"name":"cfg_if","disambiguator":[3584840542252973101,9721294085565180644]}},{"file_name":"/home/senick/.cargo/registry/src/github.com-1ecc6299db9ec823/wasm-logger-0.2.0/src/lib.rs","num":23,"id":{"name":"serde","disambiguator":[519753987879561946,14607359684181205538]}},{"file_name":"/home/senick/.cargo/registry/src/github.com-1ecc6299db9ec823/wasm-logger-0.2.0/src/lib.rs","num":24,"id":{"name":"serde_derive","disambiguator":[3688925872063788137,14358046915433064886]}},{"file_name":"/home/senick/.cargo/registry/src/github.com-1ecc6299db9ec823/wasm-logger-0.2.0/src/lib.rs","num":25,"id":{"name":"serde_json","disambiguator":[12114444146492176529,2567268844561768911]}},{"file_name":"/home/senick/.cargo/registry/src/github.com-1ecc6299db9ec823/wasm-logger-0.2.0/src/lib.rs","num":26,"id":{"name":"itoa","disambiguator":[14695026480234639197,8369693604984917264]}},{"file_name":"/home/senick/.cargo/registry/src/github.com-1ecc6299db9ec823/wasm-logger-0.2.0/src/lib.rs","num":27,"id":{"name":"ryu","disambiguator":[7841873147127009031,13843861162848439122]}},{"file_name":"/home/senick/.cargo/registry/src/github.com-1ecc6299db9ec823/wasm-logger-0.2.0/src/lib.rs","num":28,"id":{"name":"web_sys","disambiguator":[15050692937876259037,4400005687106313330]}},{"file_name":"/home/senick/.cargo/registry/src/github.com-1ecc6299db9ec823/wasm-logger-0.2.0/src/lib.rs","num":29,"id":{"name":"js_sys","disambiguator":[435510203882445435,78743200260314862]}}],"span":{"file_name":"/home/senick/.cargo/registry/src/github.com-1ecc6299db9ec823/wasm-logger-0.2.0/src/lib.rs","byte_start":0,"byte_end":5415,"line_start":1,"line_end":176,"column_start":1,"column_end":2}},"imports":[],"defs":[{"kind":"Mod","id":{"krate":0,"index":0},"span":{"file_name":"/home/senick/.cargo/registry/src/github.com-1ecc6299db9ec823/wasm-logger-0.2.0/src/lib.rs","byte_start":0,"byte_end":5415,"line_start":1,"line_end":176,"column_start":1,"column_end":2},"name":"","qualname":"::","value":"/home/senick/.cargo/registry/src/github.com-1ecc6299db9ec823/wasm-logger-0.2.0/src/lib.rs","parent":null,"children":[{"krate":0,"index":1},{"krate":0,"index":2},{"krate":0,"index":3},{"krate":0,"index":4},{"krate":0,"index":5},{"krate":0,"index":6},{"krate":0,"index":7},{"krate":0,"index":8},{"krate":0,"index":9},{"krate":0,"index":10},{"krate":0,"index":14},{"krate":0,"index":19},{"krate":0,"index":21},{"krate":0,"index":25},{"krate":0,"index":33},{"krate":0,"index":35},{"krate":0,"index":38},{"krate":0,"index":42}],"decl_id":null,"docs":" A simple logger for front end wasm web app.","sig":null,"attributes":[{"value":"/ A simple logger for front end wasm web app.","span":{"file_name":"/home/senick/.cargo/registry/src/github.com-1ecc6299db9ec823/wasm-logger-0.2.0/src/lib.rs","byte_start":0,"byte_end":47,"line_start":1,"line_end":1,"column_start":1,"column_end":48}},{"value":"/","span":{"file_name":"/home/senick/.cargo/registry/src/github.com-1ecc6299db9ec823/wasm-logger-0.2.0/src/lib.rs","byte_start":48,"byte_end":51,"line_start":2,"line_end":2,"column_start":1,"column_end":4}},{"value":"/ Please see [README](https://gitlab.com/limira-rs/wasm-logger/blob/master/README.md) for documentation.","span":{"file_name":"/home/senick/.cargo/registry/src/github.com-1ecc6299db9ec823/wasm-logger-0.2.0/src/lib.rs","byte_start":52,"byte_end":158,"line_start":3,"line_end":3,"column_start":1,"column_end":107}},{"value":"deny(missing_docs)","span":{"file_name":"/home/senick/.cargo/registry/src/github.com-1ecc6299db9ec823/wasm-logger-0.2.0/src/lib.rs","byte_start":159,"byte_end":181,"line_start":4,"line_end":4,"column_start":1,"column_end":23}}]},{"kind":"Struct","id":{"krate":0,"index":10},"span":{"file_name":"/home/senick/.cargo/registry/src/github.com-1ecc6299db9ec823/wasm-logger-0.2.0/src/lib.rs","byte_start":317,"byte_end":323,"line_start":10,"line_end":10,"column_start":12,"column_end":18},"name":"Config","qualname":"::Config","value":"Config {  }","parent":null,"children":[{"krate":0,"index":11},{"krate":0,"index":12},{"krate":0,"index":13}],"decl_id":null,"docs":" Specify what to be logged\n","sig":null,"attributes":[{"value":"/ Specify what to be logged","span":{"file_name":"/home/senick/.cargo/registry/src/github.com-1ecc6299db9ec823/wasm-logger-0.2.0/src/lib.rs","byte_start":276,"byte_end":305,"line_start":9,"line_end":9,"column_start":1,"column_end":30}}]},{"kind":"TupleVariant","id":{"krate":0,"index":15},"span":{"file_name":"/home/senick/.cargo/registry/src/github.com-1ecc6299db9ec823/wasm-logger-0.2.0/src/lib.rs","byte_start":574,"byte_end":582,"line_start":19,"line_end":19,"column_start":5,"column_end":13},"name":"SameLine","qualname":"::MessageLocation::SameLine","value":"MessageLocation::SameLine","parent":{"krate":0,"index":14},"children":[],"decl_id":null,"docs":" The message will be on the same line as other info (level, path...)\n","sig":null,"attributes":[{"value":"/ The message will be on the same line as other info (level, path...)","span":{"file_name":"/home/senick/.cargo/registry/src/github.com-1ecc6299db9ec823/wasm-logger-0.2.0/src/lib.rs","byte_start":498,"byte_end":569,"line_start":18,"line_end":18,"column_start":5,"column_end":76}}]},{"kind":"TupleVariant","id":{"krate":0,"index":17},"span":{"file_name":"/home/senick/.cargo/registry/src/github.com-1ecc6299db9ec823/wasm-logger-0.2.0/src/lib.rs","byte_start":657,"byte_end":664,"line_start":21,"line_end":21,"column_start":5,"column_end":12},"name":"NewLine","qualname":"::MessageLocation::NewLine","value":"MessageLocation::NewLine","parent":{"krate":0,"index":14},"children":[],"decl_id":null,"docs":" The message will be on its own line, a new after other info.\n","sig":null,"attributes":[{"value":"/ The message will be on its own line, a new after other info.","span":{"file_name":"/home/senick/.cargo/registry/src/github.com-1ecc6299db9ec823/wasm-logger-0.2.0/src/lib.rs","byte_start":588,"byte_end":652,"line_start":20,"line_end":20,"column_start":5,"column_end":69}}]},{"kind":"Enum","id":{"krate":0,"index":14},"span":{"file_name":"/home/senick/.cargo/registry/src/github.com-1ecc6299db9ec823/wasm-logger-0.2.0/src/lib.rs","byte_start":476,"byte_end":491,"line_start":17,"line_end":17,"column_start":10,"column_end":25},"name":"MessageLocation","qualname":"::MessageLocation","value":"pub enum MessageLocation {\n\n    /// The message will be on the same line as other info (level, path...)\n    SameLine,\n\n    /// The message will be on its own line, a new after other info.\n    NewLine,\n}","parent":null,"children":[{"krate":0,"index":15},{"krate":0,"index":17}],"decl_id":null,"docs":" Specify where the message will be logged.\n","sig":null,"attributes":[{"value":"/ Specify where the message will be logged.","span":{"file_name":"/home/senick/.cargo/registry/src/github.com-1ecc6299db9ec823/wasm-logger-0.2.0/src/lib.rs","byte_start":421,"byte_end":466,"line_start":16,"line_end":16,"column_start":1,"column_end":46}}]},{"kind":"Method","id":{"krate":0,"index":22},"span":{"file_name":"/home/senick/.cargo/registry/src/github.com-1ecc6299db9ec823/wasm-logger-0.2.0/src/lib.rs","byte_start":954,"byte_end":957,"line_start":36,"line_end":36,"column_start":12,"column_end":15},"name":"new","qualname":"<Config>::new","value":"pub fn new(Level) -> Self","parent":null,"children":[],"decl_id":null,"docs":" Specify the maximum level you want to log\n","sig":null,"attributes":[{"value":"/ Specify the maximum level you want to log","span":{"file_name":"/home/senick/.cargo/registry/src/github.com-1ecc6299db9ec823/wasm-logger-0.2.0/src/lib.rs","byte_start":897,"byte_end":942,"line_start":35,"line_end":35,"column_start":5,"column_end":50}}]},{"kind":"Method","id":{"krate":0,"index":23},"span":{"file_name":"/home/senick/.cargo/registry/src/github.com-1ecc6299db9ec823/wasm-logger-0.2.0/src/lib.rs","byte_start":1426,"byte_end":1439,"line_start":48,"line_end":48,"column_start":12,"column_end":25},"name":"module_prefix","qualname":"<Config>::module_prefix","value":"pub fn module_prefix(Self, &str) -> Self","parent":null,"children":[],"decl_id":null,"docs":" Configure the `target` of the logger. If specified, the logger\n only output for `log`s in module that its path starts with\n `module_prefix`. wasm-logger only supports single prefix. Only\n the last call to `module_prefix` has effect if you call it multiple times.\n","sig":null,"attributes":[{"value":"/ Configure the `target` of the logger. If specified, the logger","span":{"file_name":"/home/senick/.cargo/registry/src/github.com-1ecc6299db9ec823/wasm-logger-0.2.0/src/lib.rs","byte_start":1127,"byte_end":1193,"line_start":44,"line_end":44,"column_start":5,"column_end":71}},{"value":"/ only output for `log`s in module that its path starts with","span":{"file_name":"/home/senick/.cargo/registry/src/github.com-1ecc6299db9ec823/wasm-logger-0.2.0/src/lib.rs","byte_start":1198,"byte_end":1260,"line_start":45,"line_end":45,"column_start":5,"column_end":67}},{"value":"/ `module_prefix`. wasm-logger only supports single prefix. Only","span":{"file_name":"/home/senick/.cargo/registry/src/github.com-1ecc6299db9ec823/wasm-logger-0.2.0/src/lib.rs","byte_start":1265,"byte_end":1331,"line_start":46,"line_end":46,"column_start":5,"column_end":71}},{"value":"/ the last call to `module_prefix` has effect if you call it multiple times.","span":{"file_name":"/home/senick/.cargo/registry/src/github.com-1ecc6299db9ec823/wasm-logger-0.2.0/src/lib.rs","byte_start":1336,"byte_end":1414,"line_start":47,"line_end":47,"column_start":5,"column_end":83}}]},{"kind":"Method","id":{"krate":0,"index":24},"span":{"file_name":"/home/senick/.cargo/registry/src/github.com-1ecc6299db9ec823/wasm-logger-0.2.0/src/lib.rs","byte_start":1693,"byte_end":1712,"line_start":55,"line_end":55,"column_start":12,"column_end":31},"name":"message_on_new_line","qualname":"<Config>::message_on_new_line","value":"pub fn message_on_new_line(Self) -> Self","parent":null,"children":[],"decl_id":null,"docs":" Put the message on a new line, separated from other information\n such as level, file path, line number.\n","sig":null,"attributes":[{"value":"/ Put the message on a new line, separated from other information","span":{"file_name":"/home/senick/.cargo/registry/src/github.com-1ecc6299db9ec823/wasm-logger-0.2.0/src/lib.rs","byte_start":1567,"byte_end":1634,"line_start":53,"line_end":53,"column_start":5,"column_end":72}},{"value":"/ such as level, file path, line number.","span":{"file_name":"/home/senick/.cargo/registry/src/github.com-1ecc6299db9ec823/wasm-logger-0.2.0/src/lib.rs","byte_start":1639,"byte_end":1681,"line_start":54,"line_end":54,"column_start":5,"column_end":47}}]},{"kind":"Function","id":{"krate":0,"index":42},"span":{"file_name":"/home/senick/.cargo/registry/src/github.com-1ecc6299db9ec823/wasm-logger-0.2.0/src/lib.rs","byte_start":5091,"byte_end":5095,"line_start":165,"line_end":165,"column_start":8,"column_end":12},"name":"init","qualname":"::init","value":"pub fn init(Config)","parent":null,"children":[],"decl_id":null,"docs":" Initialize the logger which the given config. If failed, it will log a message to the the browser console.","sig":null,"attributes":[{"value":"/ Initialize the logger which the given config. If failed, it will log a message to the the browser console.","span":{"file_name":"/home/senick/.cargo/registry/src/github.com-1ecc6299db9ec823/wasm-logger-0.2.0/src/lib.rs","byte_start":4746,"byte_end":4856,"line_start":155,"line_end":155,"column_start":1,"column_end":111}},{"value":"/","span":{"file_name":"/home/senick/.cargo/registry/src/github.com-1ecc6299db9ec823/wasm-logger-0.2.0/src/lib.rs","byte_start":4857,"byte_end":4860,"line_start":156,"line_end":156,"column_start":1,"column_end":4}},{"value":"/ ## Examples","span":{"file_name":"/home/senick/.cargo/registry/src/github.com-1ecc6299db9ec823/wasm-logger-0.2.0/src/lib.rs","byte_start":4861,"byte_end":4876,"line_start":157,"line_end":157,"column_start":1,"column_end":16}},{"value":"/ ```rust","span":{"file_name":"/home/senick/.cargo/registry/src/github.com-1ecc6299db9ec823/wasm-logger-0.2.0/src/lib.rs","byte_start":4877,"byte_end":4888,"line_start":158,"line_end":158,"column_start":1,"column_end":12}},{"value":"/ wasm_logger::init(wasm_logger::Config::new(log::Level::Debug));","span":{"file_name":"/home/senick/.cargo/registry/src/github.com-1ecc6299db9ec823/wasm-logger-0.2.0/src/lib.rs","byte_start":4889,"byte_end":4956,"line_start":159,"line_end":159,"column_start":1,"column_end":68}},{"value":"/ ```","span":{"file_name":"/home/senick/.cargo/registry/src/github.com-1ecc6299db9ec823/wasm-logger-0.2.0/src/lib.rs","byte_start":4957,"byte_end":4964,"line_start":160,"line_end":160,"column_start":1,"column_end":8}},{"value":"/ or","span":{"file_name":"/home/senick/.cargo/registry/src/github.com-1ecc6299db9ec823/wasm-logger-0.2.0/src/lib.rs","byte_start":4965,"byte_end":4971,"line_start":161,"line_end":161,"column_start":1,"column_end":7}},{"value":"/ ```rust","span":{"file_name":"/home/senick/.cargo/registry/src/github.com-1ecc6299db9ec823/wasm-logger-0.2.0/src/lib.rs","byte_start":4972,"byte_end":4983,"line_start":162,"line_end":162,"column_start":1,"column_end":12}},{"value":"/ wasm_logger::init(wasm_logger::Config::with_prefix(log::Level::Debug, \"some::module\"));","span":{"file_name":"/home/senick/.cargo/registry/src/github.com-1ecc6299db9ec823/wasm-logger-0.2.0/src/lib.rs","byte_start":4984,"byte_end":5075,"line_start":163,"line_end":163,"column_start":1,"column_end":92}},{"value":"/ ```","span":{"file_name":"/home/senick/.cargo/registry/src/github.com-1ecc6299db9ec823/wasm-logger-0.2.0/src/lib.rs","byte_start":5076,"byte_end":5083,"line_start":164,"line_end":164,"column_start":1,"column_end":8}}]}],"impls":[{"id":0,"kind":"Direct","span":{"file_name":"/home/senick/.cargo/registry/src/github.com-1ecc6299db9ec823/wasm-logger-0.2.0/src/lib.rs","byte_start":686,"byte_end":692,"line_start":24,"line_end":24,"column_start":18,"column_end":24},"value":"","parent":null,"children":[{"krate":0,"index":20}],"docs":"","sig":null,"attributes":[]},{"id":1,"kind":"Inherent","span":{"file_name":"/home/senick/.cargo/registry/src/github.com-1ecc6299db9ec823/wasm-logger-0.2.0/src/lib.rs","byte_start":884,"byte_end":890,"line_start":34,"line_end":34,"column_start":6,"column_end":12},"value":"","parent":null,"children":[{"krate":0,"index":22},{"krate":0,"index":23},{"krate":0,"index":24}],"docs":"","sig":null,"attributes":[]},{"id":2,"kind":"Inherent","span":{"file_name":"/home/senick/.cargo/registry/src/github.com-1ecc6299db9ec823/wasm-logger-0.2.0/src/lib.rs","byte_start":2003,"byte_end":2008,"line_start":72,"line_end":72,"column_start":6,"column_end":11},"value":"","parent":null,"children":[{"krate":0,"index":34}],"docs":"","sig":null,"attributes":[]},{"id":3,"kind":"Direct","span":{"file_name":"/home/senick/.cargo/registry/src/github.com-1ecc6299db9ec823/wasm-logger-0.2.0/src/lib.rs","byte_start":2630,"byte_end":2640,"line_start":93,"line_end":93,"column_start":14,"column_end":24},"value":"","parent":null,"children":[{"krate":0,"index":39},{"krate":0,"index":40},{"krate":0,"index":41}],"docs":"","sig":null,"attributes":[]}],"refs":[],"macro_refs":[],"relations":[{"span":{"file_name":"/home/senick/.cargo/registry/src/github.com-1ecc6299db9ec823/wasm-logger-0.2.0/src/lib.rs","byte_start":686,"byte_end":692,"line_start":24,"line_end":24,"column_start":18,"column_end":24},"kind":{"Impl":{"id":0}},"from":{"krate":0,"index":10},"to":{"krate":2,"index":2044}},{"span":{"file_name":"/home/senick/.cargo/registry/src/github.com-1ecc6299db9ec823/wasm-logger-0.2.0/src/lib.rs","byte_start":884,"byte_end":890,"line_start":34,"line_end":34,"column_start":6,"column_end":12},"kind":{"Impl":{"id":1}},"from":{"krate":0,"index":10},"to":{"krate":4294967295,"index":4294967295}},{"span":{"file_name":"/home/senick/.cargo/registry/src/github.com-1ecc6299db9ec823/wasm-logger-0.2.0/src/lib.rs","byte_start":2003,"byte_end":2008,"line_start":72,"line_end":72,"column_start":6,"column_end":11},"kind":{"Impl":{"id":2}},"from":{"krate":0,"index":25},"to":{"krate":4294967295,"index":4294967295}},{"span":{"file_name":"/home/senick/.cargo/registry/src/github.com-1ecc6299db9ec823/wasm-logger-0.2.0/src/lib.rs","byte_start":2630,"byte_end":2640,"line_start":93,"line_end":93,"column_start":14,"column_end":24},"kind":{"Impl":{"id":3}},"from":{"krate":0,"index":35},"to":{"krate":18,"index":144}}]}